{"cameraMode":{"drawMode":0,"name":"Shaded","section":"Shading Mode"},"sceneLighting":true,"audioPlay":false,"sceneViewState":{"showFog":true,"showMaterialUpdate":false,"showSkybox":true,"showFlares":true,"showImageEffects":true,"showParticleSystems":true},"in2DMode":false,"pivot":{"x":-2.8255090713500978,"y":10.935293197631836,"z":-0.43611079454421999},"rotation":{"x":-0.1140461415052414,"y":-0.015799114480614663,"z":0.0018136861035600305,"w":-0.993348240852356},"size":26.034517288208009,"orthographic":false}